[{"image": "AMB_R7_C6_2018.jpg", "verified": false, "annotations": [{"label": "Agricola", "coordinates": {"x": 303.0, "y": 242.3888888888889, "width": 185.0, "height": 117.0}}, {"label": "Agricola", "coordinates": {"x": 469.25, "y": 130.8888888888889, "width": 177.5, "height": 70.0}}, {"label": "Agricola", "coordinates": {"x": 441.5, "y": 60.44444444444446, "width": 228.0, "height": 120.88888888888891}}, {"label": "Poblacion", "coordinates": {"x": 212.0, "y": 324.3888888888889, "width": 163.0, "height": 131.0}}, {"label": "Poblacion", "coordinates": {"x": 418.5, "y": 242.3888888888889, "width": 80.0, "height": 171.0}}, {"label": "Industria", "coordinates": {"x": 101.0, "y": 195.3888888888889, "width": 193.0, "height": 161.0}}, {"label": "Industria", "coordinates": {"x": 246.5, "y": 73.94444444444446, "width": 204.0, "height": 147.8888888888889}}]}]